funstruct/__init__.py
funstruct/cons.py
funstruct/frozendict.py
funstruct-0.1.2.dist-info/LICENSE
funstruct-0.1.2.dist-info/METADATA
funstruct-0.1.2.dist-info/WHEEL
funstruct-0.1.2.dist-info/RECORD
